pynlp/__init__.py
pynlp/__main__.py
pynlp/annotators.py
pynlp/client.py
pynlp/exceptions.py
pynlp/serializers.py
pynlp/wrapper.py
pynlp/protobuf/CoreNLP_pb2.py
pynlp/protobuf/__init__.py
pynlp-0.4.2.dist-info/METADATA
pynlp-0.4.2.dist-info/RECORD
pynlp-0.4.2.dist-info/WHEEL
pynlp-0.4.2.dist-info/top_level.txt
