Metadata-Version: 2.1
Name: pynlp
Version: 0.4.2
Summary: Python wrapper for Stanford CoreNLP
Home-page: http://github.com/sina-al/pynlp
Author: Sina
Author-email: s.aleyaasin@gmail.com
License: MIT
Platform: UNKNOWN
Classifier: Programming Language :: Python :: 3
Classifier: License :: OSI Approved :: MIT License
Classifier: Operating System :: OS Independent
Requires-Dist: requests
Requires-Dist: protobuf
